{
    "fields": [
        {
            "name": "name",
            "type": "String",
            "nullable": "false",
        },
        {
            "name": "name_lowercase",
            "type": "String",
            "nullable": "false",
        },
        {
            "name": "author",
            "type": "String",
            "nullable": "false",
        },
        {
            "name": "author_lowercase",
            "type": "String",
            "nullable": "false",
        },
        {
            "name": "duration",
            "type": "Integer",
            "nullable": "false",
        },
        {
            "name": "audio_url",
            "type": "String",
            "nullable": "false",
        }
    ],
    "constraints": [
        {
            "name": "unique_url",
            "definition": "UNIQUE (audio_url) ON CONFLICT REPLACE"
        },
    ]
}
